guavacado/BasicAuth.py
guavacado/Client.py
guavacado/ClientCookieStore.py
guavacado/ConnDispatcher.py
guavacado/ConnListener.py
guavacado/RawSocketDispatcher.py
guavacado/RedirectDispatcher.py
guavacado/WebDispatcher.py
guavacado/WebDocs.py
guavacado/WebFileInterface.py
guavacado/WebHost.py
guavacado/WebInterface.py
guavacado/WebRequestHandler.py
guavacado/WebSocketHandler.py
guavacado/WebSocketInterface.py
guavacado/WebSocketMessage.py
guavacado/__init__.py
guavacado/__main__.py
guavacado/http_status_codes.py
guavacado/misc.py
guavacado/version_number.py
guavacado-1.9.25.dist-info/METADATA
guavacado-1.9.25.dist-info/WHEEL
guavacado-1.9.25.dist-info/top_level.txt
guavacado-1.9.25.dist-info/RECORD
