Metadata-Version: 2.1
Name: guavacado
Version: 1.9.25
Summary: Simple Web API Hosting
Home-page: https://github.com/jhuseman/Guavacado
Author: Joshua Huseman
Author-email: jhuseman@alumni.nd.edu
License: UNKNOWN
Platform: UNKNOWN
